picologger/__init__.py
picologger/logger.py
picologger/utils.py
picologger-0.1.dist-info/LICENSE
picologger-0.1.dist-info/METADATA
picologger-0.1.dist-info/WHEEL
picologger-0.1.dist-info/top_level.txt
picologger-0.1.dist-info/RECORD
