Metadata-Version: 2.1
Name: picologger
Version: 0.1
Summary: Simple Metric logger.
Home-page: https://github.com/darkhan-ai/picologger
License: MIT
License-File: LICENSE
